{
  "settings": {
    "universe": [
      "Bitcoin",
      "Ethereum",
      "Solana"
    ],
    "tickers": [
      "BTC-USD",
      "ETH-USD",
      "SOL-USD"
    ],
    "lookback": 2,
    "top_k": 1,
    "trend_ma": 200,
    "period": "weekly",
    "start": "2016-01-01",
    "end": "2026-03-01",
    "initial": 10000
  },
  "summary": {
    "final": 70940105.8,
    "peak": 122988868.67,
    "total_return": 709301.1,
    "peak_return": 1229788.7,
    "cagr": 139.29,
    "max_dd": 60.8,
    "cash_periods": 165,
    "total_trades": 49
  },
  "trades": [
    {
      "date": "2016-01-01",
      "ticker": "BTC-USD",
      "name": "Bitcoin",
      "price": 434.334,
      "momentum_pct": 20.3,
      "equity_after": 10000
    },
    {
      "date": "2019-04-05",
      "ticker": "ETH-USD",
      "name": "Ethereum",
      "price": 165.5148,
      "momentum_pct": 53.5,
      "equity_after": 191980.12
    },
    {
      "date": "2019-04-12",
      "ticker": "BTC-USD",
      "name": "Bitcoin",
      "price": 5089.5391,
      "momentum_pct": 39.5,
      "equity_after": 191077.12
    },
    {
      "date": "2019-09-20",
      "ticker": "ETH-USD",
      "name": "Ethereum",
      "price": 218.05,
      "momentum_pct": 0.2,
      "equity_after": 382250.48
    },
    {
      "date": "2019-11-01",
      "ticker": "BTC-USD",
      "name": "Bitcoin",
      "price": 9261.1045,
      "momentum_pct": -10.5,
      "equity_after": 306275.38
    },
    {
      "date": "2020-01-31",
      "ticker": "BTC-USD",
      "name": "Bitcoin",
      "price": 9350.5293,
      "momentum_pct": 27.7,
      "equity_after": 291187.54
    },
    {
      "date": "2020-02-07",
      "ticker": "ETH-USD",
      "name": "Ethereum",
      "price": 222.7261,
      "momentum_pct": 50.3,
      "equity_after": 305058.31
    },
    {
      "date": "2020-04-24",
      "ticker": "ETH-USD",
      "name": "Ethereum",
      "price": 189.2369,
      "momentum_pct": -28.6,
      "equity_after": 182440.8
    },
    {
      "date": "2020-05-01",
      "ticker": "BTC-USD",
      "name": "Bitcoin",
      "price": 8864.7666,
      "momentum_pct": -0.1,
      "equity_after": 206525.77
    },
    {
      "date": "2020-05-22",
      "ticker": "ETH-USD",
      "name": "Ethereum",
      "price": 207.1692,
      "momentum_pct": 53.6,
      "equity_after": 213929.92
    },
    {
      "date": "2020-06-19",
      "ticker": "BTC-USD",
      "name": "Bitcoin",
      "price": 9288.0186,
      "momentum_pct": 35.0,
      "equity_after": 234550.69
    },
    {
      "date": "2020-07-03",
      "ticker": "ETH-USD",
      "name": "Ethereum",
      "price": 225.3871,
      "momentum_pct": 8.3,
      "equity_after": 229482.03
    },
    {
      "date": "2020-10-02",
      "ticker": "BTC-USD",
      "name": "Bitcoin",
      "price": 10575.9746,
      "momentum_pct": -6.0,
      "equity_after": 352529.59
    },
    {
      "date": "2021-01-08",
      "ticker": "ETH-USD",
      "name": "Ethereum",
      "price": 1224.1971,
      "momentum_pct": 175.6,
      "equity_after": 1359909.12
    },
    {
      "date": "2021-02-05",
      "ticker": "SOL-USD",
      "name": "Solana",
      "price": 6.6817,
      "momentum_pct": 264.9,
      "equity_after": 1909176.98
    },
    {
      "date": "2021-08-06",
      "ticker": "ETH-USD",
      "name": "Ethereum",
      "price": 2890.9417,
      "momentum_pct": 11.6,
      "equity_after": 11270988.99
    },
    {
      "date": "2021-08-20",
      "ticker": "SOL-USD",
      "name": "Solana",
      "price": 78.7246,
      "momentum_pct": 195.3,
      "equity_after": 12814859.68
    },
    {
      "date": "2021-11-12",
      "ticker": "BTC-USD",
      "name": "Bitcoin",
      "price": 64155.9414,
      "momentum_pct": 42.7,
      "equity_after": 37195763.38
    },
    {
      "date": "2021-11-19",
      "ticker": "SOL-USD",
      "name": "Solana",
      "price": 215.28,
      "momentum_pct": 62.9,
      "equity_after": 33696054.15
    },
    {
      "date": "2021-12-24",
      "ticker": "ETH-USD",
      "name": "Ethereum",
      "price": 4047.9829,
      "momentum_pct": -4.0,
      "equity_after": 29781937.05
    },
    {
      "date": "2022-01-07",
      "ticker": "SOL-USD",
      "name": "Solana",
      "price": 136.4028,
      "momentum_pct": -45.1,
      "equity_after": 23493180.36
    },
    {
      "date": "2023-01-13",
      "ticker": "BTC-USD",
      "name": "Bitcoin",
      "price": 19909.5742,
      "momentum_pct": 19.8,
      "equity_after": 19284343.45
    },
    {
      "date": "2023-01-20",
      "ticker": "ETH-USD",
      "name": "Ethereum",
      "price": 1659.7542,
      "momentum_pct": 49.7,
      "equity_after": 21964429.1
    },
    {
      "date": "2023-01-27",
      "ticker": "BTC-USD",
      "name": "Bitcoin",
      "price": 23078.7285,
      "momentum_pct": 42.3,
      "equity_after": 21149273.82
    },
    {
      "date": "2023-05-19",
      "ticker": "ETH-USD",
      "name": "Ethereum",
      "price": 1812.5895,
      "momentum_pct": 4.5,
      "equity_after": 24642029.08
    },
    {
      "date": "2023-06-16",
      "ticker": "BTC-USD",
      "name": "Bitcoin",
      "price": 26327.4629,
      "momentum_pct": -10.6,
      "equity_after": 23337994.4
    },
    {
      "date": "2023-07-14",
      "ticker": "SOL-USD",
      "name": "Solana",
      "price": 26.7357,
      "momentum_pct": 27.3,
      "equity_after": 26889652.08
    },
    {
      "date": "2023-10-06",
      "ticker": "SOL-USD",
      "name": "Solana",
      "price": 23.4245,
      "momentum_pct": 1.5,
      "equity_after": 21458334.91
    },
    {
      "date": "2024-02-23",
      "ticker": "ETH-USD",
      "name": "Ethereum",
      "price": 2921.6582,
      "momentum_pct": 28.6,
      "equity_after": 91565053.4
    },
    {
      "date": "2024-03-15",
      "ticker": "SOL-USD",
      "name": "Solana",
      "price": 182.9647,
      "momentum_pct": 93.6,
      "equity_after": 117062166.29
    },
    {
      "date": "2024-05-17",
      "ticker": "BTC-USD",
      "name": "Bitcoin",
      "price": 67051.875,
      "momentum_pct": -0.7,
      "equity_after": 108466901.93
    },
    {
      "date": "2024-05-24",
      "ticker": "ETH-USD",
      "name": "Ethereum",
      "price": 3726.9346,
      "momentum_pct": 3.8,
      "equity_after": 110851694.12
    },
    {
      "date": "2024-07-12",
      "ticker": "ETH-USD",
      "name": "Ethereum",
      "price": 3134.1587,
      "momentum_pct": 6.3,
      "equity_after": 88682871.51
    },
    {
      "date": "2024-07-26",
      "ticker": "SOL-USD",
      "name": "Solana",
      "price": 183.1367,
      "momentum_pct": 7.7,
      "equity_after": 92694980.41
    },
    {
      "date": "2024-08-23",
      "ticker": "SOL-USD",
      "name": "Solana",
      "price": 153.1071,
      "momentum_pct": 15.8,
      "equity_after": 70522417.42
    },
    {
      "date": "2024-09-27",
      "ticker": "BTC-USD",
      "name": "Bitcoin",
      "price": 65790.6641,
      "momentum_pct": -1.5,
      "equity_after": 63610022.52
    },
    {
      "date": "2024-10-18",
      "ticker": "BTC-USD",
      "name": "Bitcoin",
      "price": 68418.7891,
      "momentum_pct": 15.0,
      "equity_after": 60010240.63
    },
    {
      "date": "2024-11-01",
      "ticker": "SOL-USD",
      "name": "Solana",
      "price": 166.2621,
      "momentum_pct": 23.2,
      "equity_after": 60943195.96
    },
    {
      "date": "2024-12-06",
      "ticker": "ETH-USD",
      "name": "Ethereum",
      "price": 4005.8105,
      "momentum_pct": 65.4,
      "equity_after": 86890802.01
    },
    {
      "date": "2024-12-13",
      "ticker": "BTC-USD",
      "name": "Bitcoin",
      "price": 101459.2578,
      "momentum_pct": 53.6,
      "equity_after": 84838702.0
    },
    {
      "date": "2025-01-03",
      "ticker": "ETH-USD",
      "name": "Ethereum",
      "price": 3605.0098,
      "momentum_pct": 50.4,
      "equity_after": 82035953.85
    },
    {
      "date": "2025-01-10",
      "ticker": "BTC-USD",
      "name": "Bitcoin",
      "price": 94701.4531,
      "momentum_pct": 6.8,
      "equity_after": 74355320.92
    },
    {
      "date": "2025-02-14",
      "ticker": "SOL-USD",
      "name": "Solana",
      "price": 199.9357,
      "momentum_pct": -7.6,
      "equity_after": 76559655.9
    },
    {
      "date": "2025-02-21",
      "ticker": "BTC-USD",
      "name": "Bitcoin",
      "price": 96125.5469,
      "momentum_pct": 1.5,
      "equity_after": 64672228.34
    },
    {
      "date": "2025-04-25",
      "ticker": "BTC-USD",
      "name": "Bitcoin",
      "price": 94720.5,
      "momentum_pct": 3.6,
      "equity_after": 56543384.42
    },
    {
      "date": "2025-07-11",
      "ticker": "ETH-USD",
      "name": "Ethereum",
      "price": 2957.8862,
      "momentum_pct": 18.5,
      "equity_after": 70151746.08
    },
    {
      "date": "2025-09-19",
      "ticker": "SOL-USD",
      "name": "Solana",
      "price": 238.5527,
      "momentum_pct": 21.7,
      "equity_after": 106036070.75
    },
    {
      "date": "2025-10-31",
      "ticker": "BTC-USD",
      "name": "Bitcoin",
      "price": 109556.1641,
      "momentum_pct": 0.3,
      "equity_after": 83214134.93
    },
    {
      "date": "2025-11-07",
      "ticker": "ETH-USD",
      "name": "Ethereum",
      "price": 3435.301,
      "momentum_pct": -20.3,
      "equity_after": 78517219.32
    }
  ]
}